<?xml version="1.0"?>
<result><code>true</code><msg>OK</msg><data><tracks><track><id>1075</id><title>Only Acelerate  Mtb</title><descr>Visit FreeRiderHD.com for the new improved version of Free Rider. Playable on desktop, mobile and tablet.</descr><url>http://www.kanogames.com/free-rider-3/track/1075-only-acelerate-mtb</url><url_slug>1075-only-acelerate-mtb</url_slug><vehicle>MTB</vehicle><u_id>0</u_id><u_url/><u_name/><author>theoian</author><h_bg/><thumb_img>http://cdn.kanogames.com/kanogames/fr3/track_thumbs/165x105/1075-only-acelerate-mtb.jpg</thumb_img><thumb_alt>Only Acelerate  Mtb</thumb_alt><feed_img>http://cdn.kanogames.com/kanogames/fr3/track_thumbs/600x600/1075-only-acelerate-mtb.jpg</feed_img><ts>1354819102</ts><state>1</state><state_lang>Approved</state_lang><state_1>1</state_1><stats><rates>648</rates><avg_rate>3.98</avg_rate><plays>8214284</plays><best_ms>17000</best_ms><best_uid>1009679</best_uid><best_uname>pkbelg</best_uname><best_name>pkbelg</best_name><avg_rate_percentage>79.6</avg_rate_percentage><formatted_best_time/></stats></track><track><id>1007</id><title>Smooth Jumps</title><descr>Visit FreeRiderHD.com for the new improved version of Free Rider. Playable on desktop, mobile and tablet.</descr><url>http://www.kanogames.com/free-rider-3/track/1007-smooth-jumps</url><url_slug>1007-smooth-jumps</url_slug><vehicle>MTB</vehicle><u_id>0</u_id><u_url/><u_name/><author>ibauer123</author><h_bg/><thumb_img>http://cdn.kanogames.com/kanogames/fr3/track_thumbs/165x105/1007-smooth-jumps.jpg</thumb_img><thumb_alt>Smooth Jumps</thumb_alt><feed_img>http://cdn.kanogames.com/kanogames/fr3/track_thumbs/600x600/1007-smooth-jumps.jpg</feed_img><ts>1354819233</ts><state>1</state><state_lang>Approved</state_lang><state_1>1</state_1><stats><rates>3060</rates><avg_rate>4.31</avg_rate><plays>4731165</plays><best_ms>42700</best_ms><best_uid>1177930</best_uid><best_uname>sws726</best_uname><best_name>Sws726</best_name><avg_rate_percentage>86.2</avg_rate_percentage><formatted_best_time/></stats></track><track><id>1242</id><title>MTB Finshed</title><descr>Visit FreeRiderHD.com for the new improved version of Free Rider. Playable on desktop, mobile and tablet.</descr><url>http://www.kanogames.com/free-rider-3/track/1242-mtb-finshed</url><url_slug>1242-mtb-finshed</url_slug><vehicle>MTB</vehicle><u_id>0</u_id><u_url/><u_name/><author>Legend11</author><h_bg/><thumb_img>http://cdn.kanogames.com/kanogames/fr3/track_thumbs/165x105/1242-mtb-finshed.jpg</thumb_img><thumb_alt>MTB Finshed</thumb_alt><feed_img>http://cdn.kanogames.com/kanogames/fr3/track_thumbs/600x600/1242-mtb-finshed.jpg</feed_img><ts>1354819102</ts><state>1</state><state_lang>Approved</state_lang><state_1>1</state_1><stats><rates>919</rates><avg_rate>4.31</avg_rate><plays>2127172</plays><best_ms>54366</best_ms><best_uid>1735673</best_uid><best_uname>vaepor</best_uname><best_name>Vaepor</best_name><avg_rate_percentage>86.2</avg_rate_percentage><formatted_best_time/></stats></track><track><id>1070</id><title>Escape the Cave</title><descr>Visit FreeRiderHD.com for the new improved version of Free Rider. Playable on desktop, mobile and tablet.</descr><url>http://www.kanogames.com/free-rider-3/track/1070-escape-the-cave</url><url_slug>1070-escape-the-cave</url_slug><vehicle>MTB</vehicle><u_id>0</u_id><u_url/><u_name/><author>10plate</author><h_bg/><thumb_img>http://cdn.kanogames.com/kanogames/fr3/track_thumbs/165x105/1070-escape-the-cave.jpg</thumb_img><thumb_alt>Escape the Cave</thumb_alt><feed_img>http://cdn.kanogames.com/kanogames/fr3/track_thumbs/600x600/1070-escape-the-cave.jpg</feed_img><ts>1354819164</ts><state>1</state><state_lang>Approved</state_lang><state_1>1</state_1><stats><rates>1699</rates><avg_rate>4.49</avg_rate><plays>1946495</plays><best_ms>43600</best_ms><best_uid>1124181</best_uid><best_uname>llama1</best_uname><best_name>llama1</best_name><avg_rate_percentage>89.8</avg_rate_percentage><formatted_best_time/></stats></track><track><id>1138</id><title>Elements of Style</title><descr>Visit FreeRiderHD.com for the new improved version of Free Rider. Playable on desktop, mobile and tablet.</descr><url>http://www.kanogames.com/free-rider-3/track/1138-elements-of-style</url><url_slug>1138-elements-of-style</url_slug><vehicle>MTB</vehicle><u_id>0</u_id><u_url/><u_name/><author>cookiemonster</author><h_bg/><thumb_img>http://cdn.kanogames.com/kanogames/fr3/track_thumbs/165x105/1138-elements-of-style.jpg</thumb_img><thumb_alt>Elements of Style</thumb_alt><feed_img>http://cdn.kanogames.com/kanogames/fr3/track_thumbs/600x600/1138-elements-of-style.jpg</feed_img><ts>1354819262</ts><state>1</state><state_lang>Approved</state_lang><state_1>1</state_1><stats><rates>4151</rates><avg_rate>4.60</avg_rate><plays>2203648</plays><best_ms>44133</best_ms><best_uid>1735673</best_uid><best_uname>vaepor</best_uname><best_name>Vaepor</best_name><avg_rate_percentage>92</avg_rate_percentage><formatted_best_time/></stats></track><track><id>1509</id><title>dirt</title><descr>Visit FreeRiderHD.com for the new improved version of Free Rider. Playable on desktop, mobile and tablet.</descr><url>http://www.kanogames.com/free-rider-3/track/1509-dirt</url><url_slug>1509-dirt</url_slug><vehicle>MTB</vehicle><u_id>0</u_id><u_url/><u_name/><author>emjan10</author><h_bg/><thumb_img>http://cdn.kanogames.com/kanogames/fr3/track_thumbs/165x105/1509-dirt.jpg</thumb_img><thumb_alt>dirt</thumb_alt><feed_img>http://cdn.kanogames.com/kanogames/fr3/track_thumbs/600x600/1509-dirt.jpg</feed_img><ts>1354819537</ts><state>1</state><state_lang>Approved</state_lang><state_1>1</state_1><stats><rates>456</rates><avg_rate>4.23</avg_rate><plays>1462280</plays><best_ms>39833</best_ms><best_uid>1107173</best_uid><best_uname>cruise_caster2</best_uname><best_name>cruise_caster2</best_name><avg_rate_percentage>84.6</avg_rate_percentage><formatted_best_time/></stats></track><track><id>1142</id><title>Haunted Mansion</title><descr>Visit FreeRiderHD.com for the new improved version of Free Rider. Playable on desktop, mobile and tablet.</descr><url>http://www.kanogames.com/free-rider-3/track/1142-haunted-mansion</url><url_slug>1142-haunted-mansion</url_slug><vehicle>MTB</vehicle><u_id>0</u_id><u_url/><u_name/><author>iTz ChuckNorris</author><h_bg/><thumb_img>http://cdn.kanogames.com/kanogames/fr3/track_thumbs/165x105/1142-haunted-mansion.jpg</thumb_img><thumb_alt>Haunted Mansion</thumb_alt><feed_img>http://cdn.kanogames.com/kanogames/fr3/track_thumbs/600x600/1142-haunted-mansion.jpg</feed_img><ts>1354819102</ts><state>1</state><state_lang>Approved</state_lang><state_1>1</state_1><stats><rates>4698</rates><avg_rate>4.60</avg_rate><plays>1530802</plays><best_ms>48366</best_ms><best_uid>1204146</best_uid><best_uname>manolo98</best_uname><best_name>MANOLO98</best_name><avg_rate_percentage>92</avg_rate_percentage><formatted_best_time/></stats></track><track><id>1004</id><title>trekextended</title><descr>Visit FreeRiderHD.com for the new improved version of Free Rider. Playable on desktop, mobile and tablet.</descr><url>http://www.kanogames.com/free-rider-3/track/1004-trekextended</url><url_slug>1004-trekextended</url_slug><vehicle>BMX</vehicle><u_id>0</u_id><u_url/><u_name/><author>alex2571</author><h_bg/><thumb_img>http://cdn.kanogames.com/kanogames/fr3/track_thumbs/165x105/1004-trekextended.jpg</thumb_img><thumb_alt>trekextended</thumb_alt><feed_img>http://cdn.kanogames.com/kanogames/fr3/track_thumbs/600x600/1004-trekextended.jpg</feed_img><ts>1354819233</ts><state>1</state><state_lang>Approved</state_lang><state_1>1</state_1><stats><rates>6552</rates><avg_rate>4.54</avg_rate><plays>1223633</plays><best_ms>37700</best_ms><best_uid>1094146</best_uid><best_uname>legendary211</best_uname><best_name>legendary211</best_name><avg_rate_percentage>90.8</avg_rate_percentage><formatted_best_time/></stats></track><track><id>1035</id><title>Time Travel</title><descr>Visit FreeRiderHD.com for the new improved version of Free Rider. Playable on desktop, mobile and tablet.</descr><url>http://www.kanogames.com/free-rider-3/track/1035-time-travel</url><url_slug>1035-time-travel</url_slug><vehicle>BMX</vehicle><u_id>0</u_id><u_url/><u_name/><author>iTz ChuckNorris</author><h_bg/><thumb_img>http://cdn.kanogames.com/kanogames/fr3/track_thumbs/165x105/1035-time-travel.jpg</thumb_img><thumb_alt>Time Travel</thumb_alt><feed_img>http://cdn.kanogames.com/kanogames/fr3/track_thumbs/600x600/1035-time-travel.jpg</feed_img><ts>1354819102</ts><state>1</state><state_lang>Approved</state_lang><state_1>1</state_1><stats><rates>2205</rates><avg_rate>4.41</avg_rate><plays>1332777</plays><best_ms>85500</best_ms><best_uid>1176875</best_uid><best_uname>tinmew</best_uname><best_name>TinMew</best_name><avg_rate_percentage>88.2</avg_rate_percentage><formatted_best_time/></stats></track><track><id>1032</id><title>100 Jumps fixed</title><descr>Visit FreeRiderHD.com for the new improved version of Free Rider. Playable on desktop, mobile and tablet.</descr><url>http://www.kanogames.com/free-rider-3/track/1032-100-jumps-fixed</url><url_slug>1032-100-jumps-fixed</url_slug><vehicle>BMX</vehicle><u_id>0</u_id><u_url/><u_name/><author>DrManBearPig</author><h_bg/><thumb_img>http://cdn.kanogames.com/kanogames/fr3/track_thumbs/165x105/1032-100-jumps-fixed.jpg</thumb_img><thumb_alt>100 Jumps fixed</thumb_alt><feed_img>http://cdn.kanogames.com/kanogames/fr3/track_thumbs/600x600/1032-100-jumps-fixed.jpg</feed_img><ts>1354819164</ts><state>1</state><state_lang>Approved</state_lang><state_1>1</state_1><stats><rates>2673</rates><avg_rate>4.30</avg_rate><plays>2378084</plays><best_ms>215933</best_ms><best_uid>1023775</best_uid><best_uname>alberto_algh</best_uname><best_name>alberto_algh</best_name><avg_rate_percentage>86</avg_rate_percentage><formatted_best_time/></stats></track></tracks></data></result>
