<?xml version="1.0"?>
<result><code>true</code><msg>OK</msg><data><track><id>1032</id><title>100 Jumps fixed</title><descr>100 Jumps fixed is a Free Rider Community Classic Track by DrManBearPig. Enjoy!</descr><url>http://www.kanogames.com/free-rider-3/track/1032-100-jumps-fixed</url><url_slug>1032-100-jumps-fixed</url_slug><code>-18 1i 18 1i 1s 1i 68 18 6e 18 6q 17 75 16 7f 13 7o 10 81 s 89 n 8g i 8m c 8r 5 90 -3 94 -c 97 -l 9a -v 9b -1a 9c -1m 9c -1s 9c -22 9b -2e 9a -2p 97 -33 94 -3c 90 -3l 8r -3t 8m -44 8g -4a 89 -4f 81 -4k 7o -4o 7f -4r 75 -4u 6q -4v 6e -50 68 -50 1s -4m k -4m i -4m e -4n b -4q a -4u a -50,68 -k 1s -a 1q -a 1m -b 1j -e 1i -i 1i -k 1i -2g,68 -k 6d -k 6m -l 6t -o 73 -s 78 -11 7c -17 7f -1e 7g -1n 7g -1s 7g -21 7f -2a 7c -2h 78 -2n 73 -2s 6t -30 6m -33 6d -34 68 -34 1s -2q 1q -2q 1m -2p 1j -2m 1i -2i 1i -2g,-18 1i -1a 1i -1e 1h -1h 1e -1i 1a -1i 18 -1i -a -1i -c -1j -g -1m -j -1q -k -1s -k -68 -k -bs -u -c1 -u -ca -v -cj -10 -cr -12 -d3 -14 -da -17 -dg -1b -dl -1g -dq -1l -dv -1q -e3 -20 -e6 -27 -e8 -2f -ea -2n -eb -30 -ec -39 -ec -3e -ec -3j -eb -3s -ea -45 -e8 -4d -e6 -4l -e3 -4s -dv -52 -dq -57 -dl -5c -dg -5h -da -5l -d3 -5o -cr -5q -cj -5s -ca -5t -c1 -5u -bs -5u -68 -68 0 -68 2 -68 6 -67 9 -64 a -60 a -5u a -50,-bs -2q -68 -2g -66 -2g -62 -2h -5v -2k -5u -2o -5u -2q,-68 -4c -66 -4c -62 -4b -5v -48 -5u -44 -5u -42 -5u -2q,-bu -2q -c3 -2r -c7 -2s -ca -2u -cc -30 -ce -33 -cf -37 -cg -3c -cg -3e -cg -3g -cf -3l -ce -3p -cc -3s -ca -3u -c7 -40 -c3 -41 -bu -42 -bs -42 -68 -4c,-bs -2q -bu -2q##C 4m k,C 4c -3o,C 8e -1s,T -bi -1s,T 55av hfm#MTB#251040</code><vehicle>BMX</vehicle><size>81988</size><u_id>0</u_id><u_url/><u_name/><author>DrManBearPig</author><h_bg/><thumb_img>http://cdn.kanogames.com/kanogames/fr3/track_thumbs/165x105/1032-100-jumps-fixed.jpg</thumb_img><thumb_alt>100 Jumps fixed</thumb_alt><feed_img>http://cdn.kanogames.com/kanogames/fr3/track_thumbs/600x600/1032-100-jumps-fixed.jpg</feed_img><ts>1354819164</ts><state>1</state><state_lang>Approved</state_lang><state_1>1</state_1><stats><rates>2673</rates><avg_rate>4.30</avg_rate><plays>2378050</plays><best_ms>215933</best_ms><best_uid>1023775</best_uid><best_uname>alberto_algh</best_uname><best_name>alberto_algh</best_name><formatted_best_time/></stats></track></data></result>
